[
  {"title":"目前無作用", "desp": "-"},
  {"title":"A1", "desp": "藍綠光檢測室選擇"},
  {"title":"A2", "desp": "PH檢測室選擇"},
  {"title":"A3", "desp": "氨氮R1"},
  {"title":"A4", "desp": "亞硝R1"},
  {"title":"A5", "desp": "Sample"},
  {"title":"A6", "desp": "廢液觸口"},
  {"title":"A7", "desp": "RO水"},
  {"title":"C1", "desp": "池水1"},
  {"title":"C2", "desp": "池水2"},
  {"title":"C3", "desp": "池水3"},
  {"title":"C4", "desp": "池水4"},
  {"title":"目前無作用", "desp": "-"},
  {"title":"目前無作用", "desp": "-"},
  {"title":"目前無作用", "desp": "-"},
  {"title":"目前無作用", "desp": "-"},
  {"title":"目前無作用", "desp": "-"},
  {"title":"目前無作用", "desp": "-"},
  {"title":"目前無作用", "desp": "-"},
  {"title":"目前無作用", "desp": "-"},
  {"title":"目前無作用", "desp": "-"},
  {"title":"目前無作用", "desp": "-"},
  {"title":"目前無作用", "desp": "-"},
  {"title":"目前無作用", "desp": "-"},
  {"title":"目前無作用", "desp": "-"},
  {"title":"目前無作用", "desp": "-"},
  {"title":"目前無作用", "desp": "-"},
  {"title":"目前無作用", "desp": "-"},
  {"title":"目前無作用", "desp": "-"},
  {"title":"目前無作用", "desp": "-"},
  {"title":"目前無作用", "desp": "-"}
]